README.txt
setup.cfg
setup.py
anz/__init__.py
anz.cas.egg-info/PKG-INFO
anz.cas.egg-info/SOURCES.txt
anz.cas.egg-info/dependency_links.txt
anz.cas.egg-info/entry_points.txt
anz.cas.egg-info/namespace_packages.txt
anz.cas.egg-info/not-zip-safe
anz.cas.egg-info/paster_plugins.txt
anz.cas.egg-info/requires.txt
anz.cas.egg-info/top_level.txt
anz/cas/__init__.py
anz/cas/assertion.py
anz/cas/authentication.py
anz/cas/authenticationhandler.py
anz/cas/authenticationmanager.py
anz/cas/centralauthservice.py
anz/cas/configure.zcml
anz/cas/credentials.py
anz/cas/exceptions.py
anz/cas/interfaces.py
anz/cas/principal.py
anz/cas/proxyhandler.py
anz/cas/registeredservice.py
anz/cas/service.py
anz/cas/ticket.py
anz/cas/utils.py
anz/cas/validationspecification.py
anz/cas/locales/zh-cn/LC_MESSAGES/anz.cas.mo
anz/cas/locales/zh-cn/LC_MESSAGES/anz.cas.po
anz/cas/profiles/default/skins.xml
anz/cas/skins/anz_cas/anz_cas.css
anz/cas/skins/anz_cas/cas_error.pt
anz/cas/skins/anz_cas/cas_login_success.pt
anz/cas/skins/anz_cas/cas_logout.pt
anz/cas/skins/anz_cas/login_next.cpy
anz/cas/skins/anz_cas/login_next.cpy.metadata
anz/cas/skins/anz_cas/images/confirm.gif
anz/cas/skins/anz_cas/images/error.gif
anz/cas/skins/anz_cas/images/green.gif
anz/cas/skins/anz_cas/images/info.gif
anz/cas/www/add_anzcentralauthservice_form.pt
anz/cas/www/anz_cas.png
anz/cas/www/manage_services.pt
docs/HISTORY.txt
docs/INSTALL.txt
docs/LICENSE.GPL
docs/LICENSE.txt