Metadata-Version: 1.0
Name: anz.cas
Version: 1.0.1
Summary: This is an Python implementation of the server-end of JA-SIG's CAS protocol.
Home-page: http://plone.org/products/anz.cas/
Author: jiangdongjin
Author-email: eastxing@gmail.com
License: GPL
Keywords: plone cas sso
Platform: UNKNOWN
Classifier: Framework :: Plone
Classifier: Programming Language :: Python
